fudgestickle/cli.py
fudgestickle/utils.py
fudgestickle-1.3.4.7.dist-info/LICENSE
fudgestickle-1.3.4.7.dist-info/METADATA
fudgestickle-1.3.4.7.dist-info/WHEEL
fudgestickle-1.3.4.7.dist-info/entry_points.txt
fudgestickle-1.3.4.7.dist-info/top_level.txt
fudgestickle-1.3.4.7.dist-info/RECORD
