Metadata-Version: 2.1
Name: fudgestickle
Version: 1.3.4.7
Summary: a package for auto generating the code for an updated "this means war" game's score table
Home-page: https://github.com/cugzarui/fudgestickle
Author: revolution and cugz
Author-email: Roey.eshkar@gmail.com
License: MIT
Platform: UNKNOWN
Classifier: License :: OSI Approved :: MIT License
Classifier: Programming Language :: Python :: 3
Classifier: Programming Language :: Python :: 3.8
Requires-Dist: htmldom
